dreaditor/__init__.py
dreaditor/__main__.py
dreaditor/actor.py
dreaditor/actor_reference.py
dreaditor/config.py
dreaditor/constants.py
dreaditor/main_window.py
dreaditor/rom_manager.py
dreaditor/data/qt-stylesheets/main-window.txt
dreaditor/painters/collision.py
dreaditor/painters/custom_painters.py
dreaditor/painters/logicpath.py
dreaditor/painters/logicshape.py
dreaditor/painters/worldgraph.py
dreaditor/widgets/actor_data_tree.py
dreaditor/widgets/actor_data_tree_item.py
dreaditor/widgets/entity_list_tree.py
dreaditor/widgets/entity_list_tree_item.py
dreaditor/widgets/map_geometry.py
dreaditor/widgets/scenario_actor_dot.py
dreaditor/widgets/scenario_scene.py
dreaditor/widgets/scenario_viewer.py
dreaditor-0.1.5.dist-info/LICENSE
dreaditor-0.1.5.dist-info/METADATA
dreaditor-0.1.5.dist-info/WHEEL
dreaditor-0.1.5.dist-info/top_level.txt
dreaditor-0.1.5.dist-info/RECORD
