Metadata-Version: 2.1
Name: dreaditor
Version: 0.1.5
Summary: A PyQt5-based Metroid Dread data visualizer
Author: hyperbola0
License: GNU GENERAL PUBLIC LICENSE
Project-URL: Repository, https://github.com/steven11sjf/dreaditor
Classifier: Development Status :: 2 - Pre-Alpha
Classifier: Intended Audience :: Developers
Classifier: License :: OSI Approved :: GNU General Public License v3 (GPLv3)
Classifier: Operating System :: Microsoft :: Windows
Classifier: Programming Language :: Python :: 3.11
Classifier: Topic :: Games/Entertainment
Requires-Python: >=3.11
License-File: LICENSE
Requires-Dist: mercury-engine-data-structures>=0.31.1
Requires-Dist: PyQt5>=5.15.10
Requires-Dist: importlib-metadata>=7.0.2
